radolan_to_netcdf/__init__.py
radolan_to_netcdf/radolan_product_netcdf_config.py
radolan_to_netcdf/radolan_to_netcdf.py
radolan_to_netcdf/wradlib_to_radolan_bin.py
radolan_to_netcdf-0.1.0.dist-info/LICENSE
radolan_to_netcdf-0.1.0.dist-info/METADATA
radolan_to_netcdf-0.1.0.dist-info/WHEEL
radolan_to_netcdf-0.1.0.dist-info/top_level.txt
radolan_to_netcdf-0.1.0.dist-info/RECORD
